{
	"credit": "Made with Blockbench",
	"texture_size": [
		128,
		128
	],
	"textures": {
		"0": "legacycollection:custom/okee/oke-fox",
		"particle": "pnt:none"
	},
	"elements": [
		{
			"from": [
				1.5,
				-8,
				4.25
			],
			"to": [
				4.5,
				3,
				7.25
			],
			"rotation": {
				"angle": 0,
				"axis": "y",
				"origin": [
					16,
					3,
					-2
				]
			},
			"faces": {
				"north": {
					"uv": [
						0,
						8.875,
						0.75,
						11.625
					],
					"texture": "#0"
				},
				"east": {
					"uv": [
						0.75,
						8.875,
						1.5,
						11.625
					],
					"texture": "#0"
				},
				"south": {
					"uv": [
						1.5,
						8.875,
						2.25,
						11.625
					],
					"texture": "#0"
				},
				"west": {
					"uv": [
						2.25,
						8.875,
						3,
						11.625
					],
					"texture": "#0"
				},
				"up": {
					"uv": [
						1.5,
						7.25,
						2.25,
						8
					],
					"texture": "#0"
				},
				"down": {
					"uv": [
						3,
						6.75,
						3.75,
						7.5
					],
					"rotation": 180,
					"texture": "#0"
				}
			}
		}
	],
	"display": {
		"thirdperson_righthand": {
			"translation": [
				1.5,
				1,
				0.25
			],
			"scale": [
				0.29,
				0.29,
				0.29
			]
		},
		"thirdperson_lefthand": {
			"translation": [
				-1.25,
				1,
				0
			],
			"scale": [
				0.29,
				0.29,
				0.29
			]
		},
		"firstperson_righthand": {
			"rotation": [
				0,
				116,
				0
			],
			"translation": [
				1.5,
				6.75,
				0
			],
			"scale": [
				0.29,
				0.29,
				0.29
			]
		},
		"firstperson_lefthand": {
			"rotation": [
				0,
				116,
				0
			],
			"translation": [
				1.5,
				6.75,
				3.25
			],
			"scale": [
				0.29,
				0.29,
				0.29
			]
		},
		"ground": {
			"translation": [
				0,
				7.5,
				0
			],
			"scale": [
				0.47,
				0.47,
				0.47
			]
		},
		"gui": {
			"rotation": [
				22,
				141,
				0
			],
			"translation": [
				-1.25,
				5.75,
				0
			],
			"scale": [
				0.57,
				0.57,
				0.57
			]
		},
		"head": {
			"translation": [
				0,
				2.75,
				4.25
			],
			"scale": [
				1.84,
				1.84,
				1.84
			]
		},
		"fixed": {
			"translation": [
				3.5,
				7.5,
				1.5
			],
			"scale": [
				0.69,
				0.69,
				0.69
			]
		}
	},
	"groups": [
		{
			"name": "Arms",
			"origin": [
				8,
				8,
				8
			],
			"color": 0,
			"children": [
				0
			]
		}
	]
}