{"textures": {"1": "cosmetic:custom/headbands/donaldhb2"}, "elements": [{"__comment": "Voxels-4196CC", "from": [5.5, 7, 7.5], "to": [6, 8, 8.5], "faces": {"down": {"uv": [4.96, 0.96, 7.04, 3.04], "texture": "#1"}, "up": {"uv": [4.96, 0.96, 7.04, 3.04], "texture": "#1"}, "north": {"uv": [4.96, 0.96, 7.04, 3.04], "texture": "#1"}, "south": {"uv": [4.96, 0.96, 7.04, 3.04], "texture": "#1"}, "west": {"uv": [4.96, 0.96, 7.04, 3.04], "texture": "#1"}, "east": {"uv": [4.96, 0.96, 7.04, 3.04], "texture": "#1"}}}, {"__comment": "Voxels-4196CC", "from": [5.5, 7.5, 7], "to": [7, 8, 7.5], "faces": {"down": {"uv": [4.96, 0.96, 7.04, 3.04], "texture": "#1"}, "up": {"uv": [4.96, 0.96, 7.04, 3.04], "texture": "#1"}, "north": {"uv": [4.96, 0.96, 7.04, 3.04], "texture": "#1"}, "south": {"uv": [4.96, 0.96, 7.04, 3.04], "texture": "#1"}, "west": {"uv": [4.96, 0.96, 7.04, 3.04], "texture": "#1"}, "east": {"uv": [4.96, 0.96, 7.04, 3.04], "texture": "#1"}}}, {"__comment": "Voxels-4196CC", "from": [5.5, 7.5, 8.5], "to": [7, 8, 9], "faces": {"down": {"uv": [4.96, 0.96, 7.04, 3.04], "texture": "#1"}, "up": {"uv": [4.96, 0.96, 7.04, 3.04], "texture": "#1"}, "north": {"uv": [4.96, 0.96, 7.04, 3.04], "texture": "#1"}, "south": {"uv": [4.96, 0.96, 7.04, 3.04], "texture": "#1"}, "west": {"uv": [4.96, 0.96, 7.04, 3.04], "texture": "#1"}, "east": {"uv": [4.96, 0.96, 7.04, 3.04], "texture": "#1"}}}, {"__comment": "Voxels-0F0F0F", "from": [6, 6.5, 7.5], "to": [6.5, 7, 8.5], "faces": {"down": {"uv": [8.96, 0.96, 11.04, 3.04], "texture": "#1"}, "up": {"uv": [8.96, 0.96, 11.04, 3.04], "texture": "#1"}, "north": {"uv": [8.96, 0.96, 11.04, 3.04], "texture": "#1"}, "south": {"uv": [8.96, 0.96, 11.04, 3.04], "texture": "#1"}, "west": {"uv": [8.96, 0.96, 11.04, 3.04], "texture": "#1"}, "east": {"uv": [8.96, 0.96, 11.04, 3.04], "texture": "#1"}}}, {"__comment": "Voxels-4196CC", "from": [6, 7, 7], "to": [6.5, 7.5, 7.5], "faces": {"down": {"uv": [4.96, 0.96, 7.04, 3.04], "texture": "#1"}, "north": {"uv": [4.96, 0.96, 7.04, 3.04], "texture": "#1"}, "south": {"uv": [4.96, 0.96, 7.04, 3.04], "texture": "#1"}, "west": {"uv": [4.96, 0.96, 7.04, 3.04], "texture": "#1"}, "east": {"uv": [4.96, 0.96, 7.04, 3.04], "texture": "#1"}}}, {"__comment": "Voxels-4196CC", "from": [6, 7, 8.5], "to": [6.5, 7.5, 9], "faces": {"down": {"uv": [4.96, 0.96, 7.04, 3.04], "texture": "#1"}, "north": {"uv": [4.96, 0.96, 7.04, 3.04], "texture": "#1"}, "south": {"uv": [4.96, 0.96, 7.04, 3.04], "texture": "#1"}, "west": {"uv": [4.96, 0.96, 7.04, 3.04], "texture": "#1"}, "east": {"uv": [4.96, 0.96, 7.04, 3.04], "texture": "#1"}}}, {"__comment": "Voxels-4196CC", "from": [6, 7.5, 6.5], "to": [6.5, 8, 7], "faces": {"down": {"uv": [4.96, 0.96, 7.04, 3.04], "texture": "#1"}, "up": {"uv": [4.96, 0.96, 7.04, 3.04], "texture": "#1"}, "north": {"uv": [4.96, 0.96, 7.04, 3.04], "texture": "#1"}, "west": {"uv": [4.96, 0.96, 7.04, 3.04], "texture": "#1"}, "east": {"uv": [4.96, 0.96, 7.04, 3.04], "texture": "#1"}}}, {"__comment": "Voxels-4196CC", "from": [6, 7.5, 7.5], "to": [7, 8, 8.5], "faces": {"down": {"uv": [4.96, 0.96, 7.04, 3.04], "texture": "#1"}, "up": {"uv": [4.96, 0.96, 7.04, 3.04], "texture": "#1"}, "east": {"uv": [4.96, 0.96, 7.04, 3.04], "texture": "#1"}}}, {"__comment": "Voxels-4196CC", "from": [6, 7.5, 9], "to": [6.5, 8, 9.5], "faces": {"down": {"uv": [4.96, 0.96, 7.04, 3.04], "texture": "#1"}, "up": {"uv": [4.96, 0.96, 7.04, 3.04], "texture": "#1"}, "south": {"uv": [4.96, 0.96, 7.04, 3.04], "texture": "#1"}, "west": {"uv": [4.96, 0.96, 7.04, 3.04], "texture": "#1"}, "east": {"uv": [4.96, 0.96, 7.04, 3.04], "texture": "#1"}}}, {"__comment": "Voxels-4196CC", "from": [6.5, 2, 3.5], "to": [8.5, 4.5, 4], "faces": {"down": {"uv": [4.96, 0.96, 7.04, 3.04], "texture": "#1"}, "north": {"uv": [4.96, 0.96, 7.04, 3.04], "texture": "#1"}, "south": {"uv": [4.96, 0.96, 7.04, 3.04], "texture": "#1"}, "west": {"uv": [4.96, 0.96, 7.04, 3.04], "texture": "#1"}, "east": {"uv": [4.96, 0.96, 7.04, 3.04], "texture": "#1"}}}, {"__comment": "Voxels-4196CC", "from": [6.5, 2, 12], "to": [8.5, 4.5, 12.5], "faces": {"down": {"uv": [4.96, 0.96, 7.04, 3.04], "texture": "#1"}, "north": {"uv": [4.96, 0.96, 7.04, 3.04], "texture": "#1"}, "south": {"uv": [4.96, 0.96, 7.04, 3.04], "texture": "#1"}, "west": {"uv": [4.96, 0.96, 7.04, 3.04], "texture": "#1"}, "east": {"uv": [4.96, 0.96, 7.04, 3.04], "texture": "#1"}}}, {"__comment": "Voxels-F3D12C", "from": [6.5, 4.5, 3.5], "to": [8.5, 5, 4], "faces": {"north": {"uv": [12.96, 0.96, 15.04, 3.04], "texture": "#1"}, "south": {"uv": [12.96, 0.96, 15.04, 3.04], "texture": "#1"}, "west": {"uv": [12.96, 0.96, 15.04, 3.04], "texture": "#1"}, "east": {"uv": [12.96, 0.96, 15.04, 3.04], "texture": "#1"}}}, {"__comment": "Voxels-F3D12C", "from": [6.5, 4.5, 12], "to": [8.5, 5, 12.5], "faces": {"north": {"uv": [12.96, 0.96, 15.04, 3.04], "texture": "#1"}, "south": {"uv": [12.96, 0.96, 15.04, 3.04], "texture": "#1"}, "west": {"uv": [12.96, 0.96, 15.04, 3.04], "texture": "#1"}, "east": {"uv": [12.96, 0.96, 15.04, 3.04], "texture": "#1"}}}, {"__comment": "Voxels-111111", "from": [6.5, 5, 2], "to": [7, 9.5, 3.5], "faces": {"down": {"uv": [8.96, 4.96, 11.04, 7.04], "texture": "#1"}, "up": {"uv": [8.96, 4.96, 11.04, 7.04], "texture": "#1"}, "north": {"uv": [8.96, 4.96, 11.04, 7.04], "texture": "#1"}, "south": {"uv": [8.96, 4.96, 11.04, 7.04], "texture": "#1"}, "west": {"uv": [8.96, 4.96, 11.04, 7.04], "texture": "#1"}, "east": {"uv": [8.96, 4.96, 11.04, 7.04], "texture": "#1"}}}, {"__comment": "Voxels-F0F0F0", "from": [6.5, 5, 3.5], "to": [8.5, 6.5, 4], "faces": {"up": {"uv": [0.96, 4.96, 3.04, 7.04], "texture": "#1"}, "north": {"uv": [0.96, 4.96, 3.04, 7.04], "texture": "#1"}, "south": {"uv": [0.96, 4.96, 3.04, 7.04], "texture": "#1"}, "west": {"uv": [0.96, 4.96, 3.04, 7.04], "texture": "#1"}, "east": {"uv": [0.96, 4.96, 3.04, 7.04], "texture": "#1"}}}, {"__comment": "Voxels-F0F0F0", "from": [6.5, 5, 12], "to": [8.5, 6.5, 12.5], "faces": {"up": {"uv": [0.96, 4.96, 3.04, 7.04], "texture": "#1"}, "north": {"uv": [0.96, 4.96, 3.04, 7.04], "texture": "#1"}, "south": {"uv": [0.96, 4.96, 3.04, 7.04], "texture": "#1"}, "west": {"uv": [0.96, 4.96, 3.04, 7.04], "texture": "#1"}, "east": {"uv": [0.96, 4.96, 3.04, 7.04], "texture": "#1"}}}, {"__comment": "Voxels-111111", "from": [6.5, 5, 12.5], "to": [7, 9.5, 14], "faces": {"down": {"uv": [8.96, 4.96, 11.04, 7.04], "texture": "#1"}, "up": {"uv": [8.96, 4.96, 11.04, 7.04], "texture": "#1"}, "north": {"uv": [8.96, 4.96, 11.04, 7.04], "texture": "#1"}, "south": {"uv": [8.96, 4.96, 11.04, 7.04], "texture": "#1"}, "west": {"uv": [8.96, 4.96, 11.04, 7.04], "texture": "#1"}, "east": {"uv": [8.96, 4.96, 11.04, 7.04], "texture": "#1"}}}, {"__comment": "Voxels-111111", "from": [6.5, 5.5, 1], "to": [7, 9, 2], "faces": {"down": {"uv": [8.96, 4.96, 11.04, 7.04], "texture": "#1"}, "up": {"uv": [8.96, 4.96, 11.04, 7.04], "texture": "#1"}, "north": {"uv": [8.96, 4.96, 11.04, 7.04], "texture": "#1"}, "west": {"uv": [8.96, 4.96, 11.04, 7.04], "texture": "#1"}, "east": {"uv": [8.96, 4.96, 11.04, 7.04], "texture": "#1"}}}, {"__comment": "Voxels-111111", "from": [6.5, 5.5, 14], "to": [7, 9, 15], "faces": {"down": {"uv": [8.96, 4.96, 11.04, 7.04], "texture": "#1"}, "up": {"uv": [8.96, 4.96, 11.04, 7.04], "texture": "#1"}, "south": {"uv": [8.96, 4.96, 11.04, 7.04], "texture": "#1"}, "west": {"uv": [8.96, 4.96, 11.04, 7.04], "texture": "#1"}, "east": {"uv": [8.96, 4.96, 11.04, 7.04], "texture": "#1"}}}, {"__comment": "Voxels-F0F0F0", "from": [6.5, 6, 4], "to": [8.5, 6.5, 12], "faces": {"down": {"uv": [0.96, 4.96, 3.04, 7.04], "texture": "#1"}, "up": {"uv": [0.96, 4.96, 3.04, 7.04], "texture": "#1"}, "west": {"uv": [0.96, 4.96, 3.04, 7.04], "texture": "#1"}, "east": {"uv": [0.96, 4.96, 3.04, 7.04], "texture": "#1"}}}, {"__comment": "Voxels-111111", "from": [6.5, 6.5, 0.5], "to": [7, 8, 1], "faces": {"down": {"uv": [8.96, 4.96, 11.04, 7.04], "texture": "#1"}, "up": {"uv": [8.96, 4.96, 11.04, 7.04], "texture": "#1"}, "north": {"uv": [8.96, 4.96, 11.04, 7.04], "texture": "#1"}, "west": {"uv": [8.96, 4.96, 11.04, 7.04], "texture": "#1"}, "east": {"uv": [8.96, 4.96, 11.04, 7.04], "texture": "#1"}}}, {"__comment": "Voxels-111111", "from": [6.5, 6.5, 3.5], "to": [7, 9, 4.5], "faces": {"down": {"uv": [8.96, 4.96, 11.04, 7.04], "texture": "#1"}, "up": {"uv": [8.96, 4.96, 11.04, 7.04], "texture": "#1"}, "south": {"uv": [8.96, 4.96, 11.04, 7.04], "texture": "#1"}, "west": {"uv": [8.96, 4.96, 11.04, 7.04], "texture": "#1"}, "east": {"uv": [8.96, 4.96, 11.04, 7.04], "texture": "#1"}}}, {"__comment": "Voxels-111111", "from": [6.5, 6.5, 4.5], "to": [7, 8, 5], "faces": {"up": {"uv": [8.96, 4.96, 11.04, 7.04], "texture": "#1"}, "south": {"uv": [8.96, 4.96, 11.04, 7.04], "texture": "#1"}, "west": {"uv": [8.96, 4.96, 11.04, 7.04], "texture": "#1"}, "east": {"uv": [8.96, 4.96, 11.04, 7.04], "texture": "#1"}}}, {"__comment": "Voxels-0F0F0F", "from": [6.5, 6.5, 7], "to": [7, 7, 7.5], "faces": {"up": {"uv": [8.96, 0.96, 11.04, 3.04], "texture": "#1"}, "north": {"uv": [8.96, 0.96, 11.04, 3.04], "texture": "#1"}, "south": {"uv": [8.96, 0.96, 11.04, 3.04], "texture": "#1"}, "west": {"uv": [8.96, 0.96, 11.04, 3.04], "texture": "#1"}, "east": {"uv": [8.96, 0.96, 11.04, 3.04], "texture": "#1"}}}, {"__comment": "Voxels-0F0F0F", "from": [6.5, 6.5, 8.5], "to": [7, 7, 9], "faces": {"up": {"uv": [8.96, 0.96, 11.04, 3.04], "texture": "#1"}, "north": {"uv": [8.96, 0.96, 11.04, 3.04], "texture": "#1"}, "south": {"uv": [8.96, 0.96, 11.04, 3.04], "texture": "#1"}, "west": {"uv": [8.96, 0.96, 11.04, 3.04], "texture": "#1"}, "east": {"uv": [8.96, 0.96, 11.04, 3.04], "texture": "#1"}}}, {"__comment": "Voxels-0F0F0F", "from": [6.5, 6.5, 9.5], "to": [7.5, 7, 10], "faces": {"up": {"uv": [8.96, 0.96, 11.04, 3.04], "texture": "#1"}, "north": {"uv": [8.96, 0.96, 11.04, 3.04], "texture": "#1"}, "south": {"uv": [8.96, 0.96, 11.04, 3.04], "texture": "#1"}, "west": {"uv": [8.96, 0.96, 11.04, 3.04], "texture": "#1"}, "east": {"uv": [8.96, 0.96, 11.04, 3.04], "texture": "#1"}}}, {"__comment": "Voxels-0F0F0F", "from": [6.5, 6.5, 10], "to": [7, 7, 10.5], "faces": {"up": {"uv": [8.96, 0.96, 11.04, 3.04], "texture": "#1"}, "south": {"uv": [8.96, 0.96, 11.04, 3.04], "texture": "#1"}, "west": {"uv": [8.96, 0.96, 11.04, 3.04], "texture": "#1"}, "east": {"uv": [8.96, 0.96, 11.04, 3.04], "texture": "#1"}}}, {"__comment": "Voxels-111111", "from": [6.5, 6.5, 11], "to": [7, 8, 12.5], "faces": {"down": {"uv": [8.96, 4.96, 11.04, 7.04], "texture": "#1"}, "up": {"uv": [8.96, 4.96, 11.04, 7.04], "texture": "#1"}, "north": {"uv": [8.96, 4.96, 11.04, 7.04], "texture": "#1"}, "west": {"uv": [8.96, 4.96, 11.04, 7.04], "texture": "#1"}, "east": {"uv": [8.96, 4.96, 11.04, 7.04], "texture": "#1"}}}, {"__comment": "Voxels-111111", "from": [6.5, 6.5, 15], "to": [7, 8, 15.5], "faces": {"down": {"uv": [8.96, 4.96, 11.04, 7.04], "texture": "#1"}, "up": {"uv": [8.96, 4.96, 11.04, 7.04], "texture": "#1"}, "south": {"uv": [8.96, 4.96, 11.04, 7.04], "texture": "#1"}, "west": {"uv": [8.96, 4.96, 11.04, 7.04], "texture": "#1"}, "east": {"uv": [8.96, 4.96, 11.04, 7.04], "texture": "#1"}}}, {"__comment": "Voxels-4196CC", "from": [6.5, 7, 6.5], "to": [9, 7.5, 7], "faces": {"down": {"uv": [4.96, 0.96, 7.04, 3.04], "texture": "#1"}, "up": {"uv": [4.96, 0.96, 7.04, 3.04], "texture": "#1"}, "north": {"uv": [4.96, 0.96, 7.04, 3.04], "texture": "#1"}, "south": {"uv": [4.96, 0.96, 7.04, 3.04], "texture": "#1"}, "west": {"uv": [4.96, 0.96, 7.04, 3.04], "texture": "#1"}, "east": {"uv": [4.96, 0.96, 7.04, 3.04], "texture": "#1"}}}, {"__comment": "Voxels-4196CC", "from": [6.5, 7, 9], "to": [9, 7.5, 9.5], "faces": {"down": {"uv": [4.96, 0.96, 7.04, 3.04], "texture": "#1"}, "up": {"uv": [4.96, 0.96, 7.04, 3.04], "texture": "#1"}, "north": {"uv": [4.96, 0.96, 7.04, 3.04], "texture": "#1"}, "south": {"uv": [4.96, 0.96, 7.04, 3.04], "texture": "#1"}, "west": {"uv": [4.96, 0.96, 7.04, 3.04], "texture": "#1"}, "east": {"uv": [4.96, 0.96, 7.04, 3.04], "texture": "#1"}}}, {"__comment": "Voxels-111111", "from": [6.5, 8, 11.5], "to": [7, 9, 12.5], "faces": {"up": {"uv": [8.96, 4.96, 11.04, 7.04], "texture": "#1"}, "north": {"uv": [8.96, 4.96, 11.04, 7.04], "texture": "#1"}, "west": {"uv": [8.96, 4.96, 11.04, 7.04], "texture": "#1"}, "east": {"uv": [8.96, 4.96, 11.04, 7.04], "texture": "#1"}}}, {"__comment": "Voxels-E2C744", "from": [7, 0, 3.5], "to": [8, 1.5, 4], "faces": {"down": {"uv": [4.96, 4.96, 7.04, 7.04], "texture": "#1", "cullface": "down"}, "north": {"uv": [4.96, 4.96, 7.04, 7.04], "texture": "#1"}, "south": {"uv": [4.96, 4.96, 7.04, 7.04], "texture": "#1"}, "west": {"uv": [4.96, 4.96, 7.04, 7.04], "texture": "#1"}, "east": {"uv": [4.96, 4.96, 7.04, 7.04], "texture": "#1"}}}, {"__comment": "Voxels-E2C744", "from": [7, 0, 12], "to": [8, 1.5, 12.5], "faces": {"down": {"uv": [4.96, 4.96, 7.04, 7.04], "texture": "#1", "cullface": "down"}, "north": {"uv": [4.96, 4.96, 7.04, 7.04], "texture": "#1"}, "south": {"uv": [4.96, 4.96, 7.04, 7.04], "texture": "#1"}, "west": {"uv": [4.96, 4.96, 7.04, 7.04], "texture": "#1"}, "east": {"uv": [4.96, 4.96, 7.04, 7.04], "texture": "#1"}}}, {"__comment": "Voxels-4196CC", "from": [7, 1.5, 3.5], "to": [8, 2, 4], "faces": {"north": {"uv": [4.96, 0.96, 7.04, 3.04], "texture": "#1"}, "south": {"uv": [4.96, 0.96, 7.04, 3.04], "texture": "#1"}, "west": {"uv": [4.96, 0.96, 7.04, 3.04], "texture": "#1"}, "east": {"uv": [4.96, 0.96, 7.04, 3.04], "texture": "#1"}}}, {"__comment": "Voxels-4196CC", "from": [7, 1.5, 12], "to": [8, 2, 12.5], "faces": {"north": {"uv": [4.96, 0.96, 7.04, 3.04], "texture": "#1"}, "south": {"uv": [4.96, 0.96, 7.04, 3.04], "texture": "#1"}, "west": {"uv": [4.96, 0.96, 7.04, 3.04], "texture": "#1"}, "east": {"uv": [4.96, 0.96, 7.04, 3.04], "texture": "#1"}}}, {"__comment": "Voxels-0F0F0F", "from": [7, 4.5, 2], "to": [7.5, 5, 3.5], "faces": {"down": {"uv": [8.96, 0.96, 11.04, 3.04], "texture": "#1"}, "up": {"uv": [8.96, 0.96, 11.04, 3.04], "texture": "#1"}, "north": {"uv": [8.96, 0.96, 11.04, 3.04], "texture": "#1"}, "west": {"uv": [8.96, 0.96, 11.04, 3.04], "texture": "#1"}, "east": {"uv": [8.96, 0.96, 11.04, 3.04], "texture": "#1"}}}, {"__comment": "Voxels-0F0F0F", "from": [7, 4.5, 12.5], "to": [7.5, 5, 14], "faces": {"down": {"uv": [8.96, 0.96, 11.04, 3.04], "texture": "#1"}, "up": {"uv": [8.96, 0.96, 11.04, 3.04], "texture": "#1"}, "south": {"uv": [8.96, 0.96, 11.04, 3.04], "texture": "#1"}, "west": {"uv": [8.96, 0.96, 11.04, 3.04], "texture": "#1"}, "east": {"uv": [8.96, 0.96, 11.04, 3.04], "texture": "#1"}}}, {"__comment": "Voxels-0F0F0F", "from": [7, 5, 1], "to": [7.5, 5.5, 2], "faces": {"down": {"uv": [8.96, 0.96, 11.04, 3.04], "texture": "#1"}, "up": {"uv": [8.96, 0.96, 11.04, 3.04], "texture": "#1"}, "north": {"uv": [8.96, 0.96, 11.04, 3.04], "texture": "#1"}, "south": {"uv": [8.96, 0.96, 11.04, 3.04], "texture": "#1"}, "west": {"uv": [8.96, 0.96, 11.04, 3.04], "texture": "#1"}, "east": {"uv": [8.96, 0.96, 11.04, 3.04], "texture": "#1"}}}, {"__comment": "Voxels-0F0F0F", "from": [7, 5, 14], "to": [7.5, 5.5, 15], "faces": {"down": {"uv": [8.96, 0.96, 11.04, 3.04], "texture": "#1"}, "up": {"uv": [8.96, 0.96, 11.04, 3.04], "texture": "#1"}, "north": {"uv": [8.96, 0.96, 11.04, 3.04], "texture": "#1"}, "south": {"uv": [8.96, 0.96, 11.04, 3.04], "texture": "#1"}, "west": {"uv": [8.96, 0.96, 11.04, 3.04], "texture": "#1"}, "east": {"uv": [8.96, 0.96, 11.04, 3.04], "texture": "#1"}}}, {"__comment": "Voxels-0F0F0F", "from": [7, 5.5, 0.5], "to": [7.5, 6.5, 1], "faces": {"down": {"uv": [8.96, 0.96, 11.04, 3.04], "texture": "#1"}, "up": {"uv": [8.96, 0.96, 11.04, 3.04], "texture": "#1"}, "north": {"uv": [8.96, 0.96, 11.04, 3.04], "texture": "#1"}, "south": {"uv": [8.96, 0.96, 11.04, 3.04], "texture": "#1"}, "west": {"uv": [8.96, 0.96, 11.04, 3.04], "texture": "#1"}, "east": {"uv": [8.96, 0.96, 11.04, 3.04], "texture": "#1"}}}, {"__comment": "Voxels-0F0F0F", "from": [7, 5.5, 15], "to": [7.5, 6.5, 15.5], "faces": {"down": {"uv": [8.96, 0.96, 11.04, 3.04], "texture": "#1"}, "up": {"uv": [8.96, 0.96, 11.04, 3.04], "texture": "#1"}, "north": {"uv": [8.96, 0.96, 11.04, 3.04], "texture": "#1"}, "south": {"uv": [8.96, 0.96, 11.04, 3.04], "texture": "#1"}, "west": {"uv": [8.96, 0.96, 11.04, 3.04], "texture": "#1"}, "east": {"uv": [8.96, 0.96, 11.04, 3.04], "texture": "#1"}}}, {"__comment": "Voxels-0F0F0F", "from": [7, 6.5, 0], "to": [7.5, 8, 0.5], "faces": {"down": {"uv": [8.96, 0.96, 11.04, 3.04], "texture": "#1"}, "up": {"uv": [8.96, 0.96, 11.04, 3.04], "texture": "#1"}, "north": {"uv": [8.96, 0.96, 11.04, 3.04], "texture": "#1", "cullface": "north"}, "south": {"uv": [8.96, 0.96, 11.04, 3.04], "texture": "#1"}, "west": {"uv": [8.96, 0.96, 11.04, 3.04], "texture": "#1"}, "east": {"uv": [8.96, 0.96, 11.04, 3.04], "texture": "#1"}}}, {"__comment": "Voxels-111111", "from": [7, 6.5, 2.5], "to": [8, 7, 3], "faces": {"down": {"uv": [8.96, 4.96, 11.04, 7.04], "texture": "#1"}, "up": {"uv": [8.96, 4.96, 11.04, 7.04], "texture": "#1"}, "north": {"uv": [8.96, 4.96, 11.04, 7.04], "texture": "#1"}, "south": {"uv": [8.96, 4.96, 11.04, 7.04], "texture": "#1"}, "east": {"uv": [8.96, 4.96, 11.04, 7.04], "texture": "#1"}}}, {"__comment": "Voxels-0F0F0F", "from": [7, 6.5, 5], "to": [7.5, 8, 5.5], "faces": {"up": {"uv": [8.96, 0.96, 11.04, 3.04], "texture": "#1"}, "north": {"uv": [8.96, 0.96, 11.04, 3.04], "texture": "#1"}, "south": {"uv": [8.96, 0.96, 11.04, 3.04], "texture": "#1"}, "west": {"uv": [8.96, 0.96, 11.04, 3.04], "texture": "#1"}, "east": {"uv": [8.96, 0.96, 11.04, 3.04], "texture": "#1"}}}, {"__comment": "Voxels-0F0F0F", "from": [7, 6.5, 6.5], "to": [8.5, 7, 7], "faces": {"north": {"uv": [8.96, 0.96, 11.04, 3.04], "texture": "#1"}, "south": {"uv": [8.96, 0.96, 11.04, 3.04], "texture": "#1"}, "west": {"uv": [8.96, 0.96, 11.04, 3.04], "texture": "#1"}, "east": {"uv": [8.96, 0.96, 11.04, 3.04], "texture": "#1"}}}, {"__comment": "Voxels-0F0F0F", "from": [7, 6.5, 9], "to": [8.5, 7, 9.5], "faces": {"north": {"uv": [8.96, 0.96, 11.04, 3.04], "texture": "#1"}, "south": {"uv": [8.96, 0.96, 11.04, 3.04], "texture": "#1"}, "west": {"uv": [8.96, 0.96, 11.04, 3.04], "texture": "#1"}, "east": {"uv": [8.96, 0.96, 11.04, 3.04], "texture": "#1"}}}, {"__comment": "Voxels-0F0F0F", "from": [7, 6.5, 10.5], "to": [7.5, 8, 11], "faces": {"up": {"uv": [8.96, 0.96, 11.04, 3.04], "texture": "#1"}, "north": {"uv": [8.96, 0.96, 11.04, 3.04], "texture": "#1"}, "south": {"uv": [8.96, 0.96, 11.04, 3.04], "texture": "#1"}, "west": {"uv": [8.96, 0.96, 11.04, 3.04], "texture": "#1"}, "east": {"uv": [8.96, 0.96, 11.04, 3.04], "texture": "#1"}}}, {"__comment": "Voxels-111111", "from": [7, 6.5, 13], "to": [8, 7, 13.5], "faces": {"down": {"uv": [8.96, 4.96, 11.04, 7.04], "texture": "#1"}, "up": {"uv": [8.96, 4.96, 11.04, 7.04], "texture": "#1"}, "north": {"uv": [8.96, 4.96, 11.04, 7.04], "texture": "#1"}, "south": {"uv": [8.96, 4.96, 11.04, 7.04], "texture": "#1"}, "east": {"uv": [8.96, 4.96, 11.04, 7.04], "texture": "#1"}}}, {"__comment": "Voxels-0F0F0F", "from": [7, 6.5, 15.5], "to": [7.5, 8, 16], "faces": {"down": {"uv": [8.96, 0.96, 11.04, 3.04], "texture": "#1"}, "up": {"uv": [8.96, 0.96, 11.04, 3.04], "texture": "#1"}, "north": {"uv": [8.96, 0.96, 11.04, 3.04], "texture": "#1"}, "south": {"uv": [8.96, 0.96, 11.04, 3.04], "texture": "#1", "cullface": "south"}, "west": {"uv": [8.96, 0.96, 11.04, 3.04], "texture": "#1"}, "east": {"uv": [8.96, 0.96, 11.04, 3.04], "texture": "#1"}}}, {"__comment": "Voxels-111111", "from": [7, 7, 2], "to": [8, 7.5, 2.5], "faces": {"down": {"uv": [8.96, 4.96, 11.04, 7.04], "texture": "#1"}, "up": {"uv": [8.96, 4.96, 11.04, 7.04], "texture": "#1"}, "north": {"uv": [8.96, 4.96, 11.04, 7.04], "texture": "#1"}, "south": {"uv": [8.96, 4.96, 11.04, 7.04], "texture": "#1"}, "east": {"uv": [8.96, 4.96, 11.04, 7.04], "texture": "#1"}}}, {"__comment": "Voxels-111111", "from": [7, 7, 3], "to": [8, 7.5, 3.5], "faces": {"down": {"uv": [8.96, 4.96, 11.04, 7.04], "texture": "#1"}, "up": {"uv": [8.96, 4.96, 11.04, 7.04], "texture": "#1"}, "north": {"uv": [8.96, 4.96, 11.04, 7.04], "texture": "#1"}, "south": {"uv": [8.96, 4.96, 11.04, 7.04], "texture": "#1"}, "east": {"uv": [8.96, 4.96, 11.04, 7.04], "texture": "#1"}}}, {"__comment": "Voxels-4196CC", "from": [7, 7, 6], "to": [8.5, 7.5, 6.5], "faces": {"down": {"uv": [4.96, 0.96, 7.04, 3.04], "texture": "#1"}, "up": {"uv": [4.96, 0.96, 7.04, 3.04], "texture": "#1"}, "north": {"uv": [4.96, 0.96, 7.04, 3.04], "texture": "#1"}, "west": {"uv": [4.96, 0.96, 7.04, 3.04], "texture": "#1"}, "east": {"uv": [4.96, 0.96, 7.04, 3.04], "texture": "#1"}}}, {"__comment": "Voxels-4196CC", "from": [7, 7, 7], "to": [8, 7.5, 9], "faces": {"down": {"uv": [4.96, 0.96, 7.04, 3.04], "texture": "#1"}, "up": {"uv": [4.96, 0.96, 7.04, 3.04], "texture": "#1"}, "west": {"uv": [4.96, 0.96, 7.04, 3.04], "texture": "#1"}, "east": {"uv": [4.96, 0.96, 7.04, 3.04], "texture": "#1"}}}, {"__comment": "Voxels-4196CC", "from": [7, 7, 9.5], "to": [8.5, 7.5, 10], "faces": {"down": {"uv": [4.96, 0.96, 7.04, 3.04], "texture": "#1"}, "up": {"uv": [4.96, 0.96, 7.04, 3.04], "texture": "#1"}, "south": {"uv": [4.96, 0.96, 7.04, 3.04], "texture": "#1"}, "west": {"uv": [4.96, 0.96, 7.04, 3.04], "texture": "#1"}, "east": {"uv": [4.96, 0.96, 7.04, 3.04], "texture": "#1"}}}, {"__comment": "Voxels-111111", "from": [7, 7, 12.5], "to": [8, 7.5, 13], "faces": {"down": {"uv": [8.96, 4.96, 11.04, 7.04], "texture": "#1"}, "up": {"uv": [8.96, 4.96, 11.04, 7.04], "texture": "#1"}, "north": {"uv": [8.96, 4.96, 11.04, 7.04], "texture": "#1"}, "south": {"uv": [8.96, 4.96, 11.04, 7.04], "texture": "#1"}, "east": {"uv": [8.96, 4.96, 11.04, 7.04], "texture": "#1"}}}, {"__comment": "Voxels-111111", "from": [7, 7, 13.5], "to": [8, 7.5, 14], "faces": {"down": {"uv": [8.96, 4.96, 11.04, 7.04], "texture": "#1"}, "up": {"uv": [8.96, 4.96, 11.04, 7.04], "texture": "#1"}, "north": {"uv": [8.96, 4.96, 11.04, 7.04], "texture": "#1"}, "south": {"uv": [8.96, 4.96, 11.04, 7.04], "texture": "#1"}, "east": {"uv": [8.96, 4.96, 11.04, 7.04], "texture": "#1"}}}, {"__comment": "Voxels-111111", "from": [7, 7.5, 2.5], "to": [8, 8, 3], "faces": {"down": {"uv": [8.96, 4.96, 11.04, 7.04], "texture": "#1"}, "up": {"uv": [8.96, 4.96, 11.04, 7.04], "texture": "#1"}, "north": {"uv": [8.96, 4.96, 11.04, 7.04], "texture": "#1"}, "south": {"uv": [8.96, 4.96, 11.04, 7.04], "texture": "#1"}, "east": {"uv": [8.96, 4.96, 11.04, 7.04], "texture": "#1"}}}, {"__comment": "Voxels-111111", "from": [7, 7.5, 13], "to": [8, 8, 13.5], "faces": {"down": {"uv": [8.96, 4.96, 11.04, 7.04], "texture": "#1"}, "up": {"uv": [8.96, 4.96, 11.04, 7.04], "texture": "#1"}, "north": {"uv": [8.96, 4.96, 11.04, 7.04], "texture": "#1"}, "south": {"uv": [8.96, 4.96, 11.04, 7.04], "texture": "#1"}, "east": {"uv": [8.96, 4.96, 11.04, 7.04], "texture": "#1"}}}, {"__comment": "Voxels-0F0F0F", "from": [7, 8, 0.5], "to": [7.5, 9, 1], "faces": {"down": {"uv": [8.96, 0.96, 11.04, 3.04], "texture": "#1"}, "up": {"uv": [8.96, 0.96, 11.04, 3.04], "texture": "#1"}, "north": {"uv": [8.96, 0.96, 11.04, 3.04], "texture": "#1"}, "south": {"uv": [8.96, 0.96, 11.04, 3.04], "texture": "#1"}, "west": {"uv": [8.96, 0.96, 11.04, 3.04], "texture": "#1"}, "east": {"uv": [8.96, 0.96, 11.04, 3.04], "texture": "#1"}}}, {"__comment": "Voxels-111111", "from": [7, 8, 4.5], "to": [7.5, 9, 5], "faces": {"down": {"uv": [8.96, 4.96, 11.04, 7.04], "texture": "#1"}, "up": {"uv": [8.96, 4.96, 11.04, 7.04], "texture": "#1"}, "north": {"uv": [8.96, 4.96, 11.04, 7.04], "texture": "#1"}, "south": {"uv": [8.96, 4.96, 11.04, 7.04], "texture": "#1"}, "west": {"uv": [8.96, 4.96, 11.04, 7.04], "texture": "#1"}, "east": {"uv": [8.96, 4.96, 11.04, 7.04], "texture": "#1"}}}, {"__comment": "Voxels-0F0F0F", "from": [7, 8, 11], "to": [7.5, 9, 11.5], "faces": {"down": {"uv": [8.96, 0.96, 11.04, 3.04], "texture": "#1"}, "up": {"uv": [8.96, 0.96, 11.04, 3.04], "texture": "#1"}, "north": {"uv": [8.96, 0.96, 11.04, 3.04], "texture": "#1"}, "south": {"uv": [8.96, 0.96, 11.04, 3.04], "texture": "#1"}, "west": {"uv": [8.96, 0.96, 11.04, 3.04], "texture": "#1"}, "east": {"uv": [8.96, 0.96, 11.04, 3.04], "texture": "#1"}}}, {"__comment": "Voxels-0F0F0F", "from": [7, 8, 15], "to": [7.5, 9, 15.5], "faces": {"down": {"uv": [8.96, 0.96, 11.04, 3.04], "texture": "#1"}, "up": {"uv": [8.96, 0.96, 11.04, 3.04], "texture": "#1"}, "north": {"uv": [8.96, 0.96, 11.04, 3.04], "texture": "#1"}, "south": {"uv": [8.96, 0.96, 11.04, 3.04], "texture": "#1"}, "west": {"uv": [8.96, 0.96, 11.04, 3.04], "texture": "#1"}, "east": {"uv": [8.96, 0.96, 11.04, 3.04], "texture": "#1"}}}, {"__comment": "Voxels-0F0F0F", "from": [7, 9, 1], "to": [7.5, 9.5, 2], "faces": {"down": {"uv": [8.96, 0.96, 11.04, 3.04], "texture": "#1"}, "up": {"uv": [8.96, 0.96, 11.04, 3.04], "texture": "#1"}, "north": {"uv": [8.96, 0.96, 11.04, 3.04], "texture": "#1"}, "south": {"uv": [8.96, 0.96, 11.04, 3.04], "texture": "#1"}, "west": {"uv": [8.96, 0.96, 11.04, 3.04], "texture": "#1"}, "east": {"uv": [8.96, 0.96, 11.04, 3.04], "texture": "#1"}}}, {"__comment": "Voxels-111111", "from": [7, 9, 3.5], "to": [7.5, 9.5, 4.5], "faces": {"down": {"uv": [8.96, 4.96, 11.04, 7.04], "texture": "#1"}, "up": {"uv": [8.96, 4.96, 11.04, 7.04], "texture": "#1"}, "north": {"uv": [8.96, 4.96, 11.04, 7.04], "texture": "#1"}, "south": {"uv": [8.96, 4.96, 11.04, 7.04], "texture": "#1"}, "west": {"uv": [8.96, 4.96, 11.04, 7.04], "texture": "#1"}, "east": {"uv": [8.96, 4.96, 11.04, 7.04], "texture": "#1"}}}, {"__comment": "Voxels-0F0F0F", "from": [7, 9, 11.5], "to": [7.5, 9.5, 12.5], "faces": {"down": {"uv": [8.96, 0.96, 11.04, 3.04], "texture": "#1"}, "up": {"uv": [8.96, 0.96, 11.04, 3.04], "texture": "#1"}, "north": {"uv": [8.96, 0.96, 11.04, 3.04], "texture": "#1"}, "south": {"uv": [8.96, 0.96, 11.04, 3.04], "texture": "#1"}, "west": {"uv": [8.96, 0.96, 11.04, 3.04], "texture": "#1"}, "east": {"uv": [8.96, 0.96, 11.04, 3.04], "texture": "#1"}}}, {"__comment": "Voxels-0F0F0F", "from": [7, 9, 14], "to": [7.5, 9.5, 15], "faces": {"down": {"uv": [8.96, 0.96, 11.04, 3.04], "texture": "#1"}, "up": {"uv": [8.96, 0.96, 11.04, 3.04], "texture": "#1"}, "north": {"uv": [8.96, 0.96, 11.04, 3.04], "texture": "#1"}, "south": {"uv": [8.96, 0.96, 11.04, 3.04], "texture": "#1"}, "west": {"uv": [8.96, 0.96, 11.04, 3.04], "texture": "#1"}, "east": {"uv": [8.96, 0.96, 11.04, 3.04], "texture": "#1"}}}, {"__comment": "Voxels-111111", "from": [7, 9.5, 2], "to": [7.5, 10, 3.5], "faces": {"down": {"uv": [8.96, 4.96, 11.04, 7.04], "texture": "#1"}, "up": {"uv": [8.96, 4.96, 11.04, 7.04], "texture": "#1"}, "north": {"uv": [8.96, 4.96, 11.04, 7.04], "texture": "#1"}, "south": {"uv": [8.96, 4.96, 11.04, 7.04], "texture": "#1"}, "west": {"uv": [8.96, 4.96, 11.04, 7.04], "texture": "#1"}, "east": {"uv": [8.96, 4.96, 11.04, 7.04], "texture": "#1"}}}, {"__comment": "Voxels-0F0F0F", "from": [7, 9.5, 12.5], "to": [7.5, 10, 14], "faces": {"down": {"uv": [8.96, 0.96, 11.04, 3.04], "texture": "#1"}, "up": {"uv": [8.96, 0.96, 11.04, 3.04], "texture": "#1"}, "north": {"uv": [8.96, 0.96, 11.04, 3.04], "texture": "#1"}, "south": {"uv": [8.96, 0.96, 11.04, 3.04], "texture": "#1"}, "west": {"uv": [8.96, 0.96, 11.04, 3.04], "texture": "#1"}, "east": {"uv": [8.96, 0.96, 11.04, 3.04], "texture": "#1"}}}, {"__comment": "Voxels-111111", "from": [7.5, 5, 2], "to": [8, 7, 2.5], "faces": {"down": {"uv": [8.96, 4.96, 11.04, 7.04], "texture": "#1"}, "north": {"uv": [8.96, 4.96, 11.04, 7.04], "texture": "#1"}, "south": {"uv": [8.96, 4.96, 11.04, 7.04], "texture": "#1"}, "west": {"uv": [8.96, 4.96, 11.04, 7.04], "texture": "#1"}, "east": {"uv": [8.96, 4.96, 11.04, 7.04], "texture": "#1"}}}, {"__comment": "Voxels-111111", "from": [7.5, 5, 2.5], "to": [8, 6.5, 3.5], "faces": {"down": {"uv": [8.96, 4.96, 11.04, 7.04], "texture": "#1"}, "up": {"uv": [8.96, 4.96, 11.04, 7.04], "texture": "#1"}, "west": {"uv": [8.96, 4.96, 11.04, 7.04], "texture": "#1"}, "east": {"uv": [8.96, 4.96, 11.04, 7.04], "texture": "#1"}}}, {"__comment": "Voxels-111111", "from": [7.5, 5, 12.5], "to": [8, 7, 13], "faces": {"down": {"uv": [8.96, 4.96, 11.04, 7.04], "texture": "#1"}, "north": {"uv": [8.96, 4.96, 11.04, 7.04], "texture": "#1"}, "south": {"uv": [8.96, 4.96, 11.04, 7.04], "texture": "#1"}, "west": {"uv": [8.96, 4.96, 11.04, 7.04], "texture": "#1"}, "east": {"uv": [8.96, 4.96, 11.04, 7.04], "texture": "#1"}}}, {"__comment": "Voxels-111111", "from": [7.5, 5, 13], "to": [8, 6.5, 14], "faces": {"down": {"uv": [8.96, 4.96, 11.04, 7.04], "texture": "#1"}, "up": {"uv": [8.96, 4.96, 11.04, 7.04], "texture": "#1"}, "south": {"uv": [8.96, 4.96, 11.04, 7.04], "texture": "#1"}, "west": {"uv": [8.96, 4.96, 11.04, 7.04], "texture": "#1"}, "east": {"uv": [8.96, 4.96, 11.04, 7.04], "texture": "#1"}}}, {"__comment": "Voxels-111111", "from": [7.5, 5.5, 1], "to": [8, 9, 2], "faces": {"down": {"uv": [8.96, 4.96, 11.04, 7.04], "texture": "#1"}, "up": {"uv": [8.96, 4.96, 11.04, 7.04], "texture": "#1"}, "north": {"uv": [8.96, 4.96, 11.04, 7.04], "texture": "#1"}, "south": {"uv": [8.96, 4.96, 11.04, 7.04], "texture": "#1"}, "west": {"uv": [8.96, 4.96, 11.04, 7.04], "texture": "#1"}, "east": {"uv": [8.96, 4.96, 11.04, 7.04], "texture": "#1"}}}, {"__comment": "Voxels-111111", "from": [7.5, 5.5, 14], "to": [8, 9, 15], "faces": {"down": {"uv": [8.96, 4.96, 11.04, 7.04], "texture": "#1"}, "up": {"uv": [8.96, 4.96, 11.04, 7.04], "texture": "#1"}, "north": {"uv": [8.96, 4.96, 11.04, 7.04], "texture": "#1"}, "south": {"uv": [8.96, 4.96, 11.04, 7.04], "texture": "#1"}, "west": {"uv": [8.96, 4.96, 11.04, 7.04], "texture": "#1"}, "east": {"uv": [8.96, 4.96, 11.04, 7.04], "texture": "#1"}}}, {"__comment": "Voxels-111111", "from": [7.5, 6.5, 0.5], "to": [8, 8, 1], "faces": {"down": {"uv": [8.96, 4.96, 11.04, 7.04], "texture": "#1"}, "up": {"uv": [8.96, 4.96, 11.04, 7.04], "texture": "#1"}, "north": {"uv": [8.96, 4.96, 11.04, 7.04], "texture": "#1"}, "west": {"uv": [8.96, 4.96, 11.04, 7.04], "texture": "#1"}, "east": {"uv": [8.96, 4.96, 11.04, 7.04], "texture": "#1"}}}, {"__comment": "Voxels-111111", "from": [7.5, 6.5, 3], "to": [8, 7, 5], "faces": {"down": {"uv": [8.96, 4.96, 11.04, 7.04], "texture": "#1"}, "up": {"uv": [8.96, 4.96, 11.04, 7.04], "texture": "#1"}, "south": {"uv": [8.96, 4.96, 11.04, 7.04], "texture": "#1"}, "west": {"uv": [8.96, 4.96, 11.04, 7.04], "texture": "#1"}, "east": {"uv": [8.96, 4.96, 11.04, 7.04], "texture": "#1"}}}, {"__comment": "Voxels-111111", "from": [7.5, 6.5, 11], "to": [8, 8, 12.5], "faces": {"down": {"uv": [8.96, 4.96, 11.04, 7.04], "texture": "#1"}, "up": {"uv": [8.96, 4.96, 11.04, 7.04], "texture": "#1"}, "north": {"uv": [8.96, 4.96, 11.04, 7.04], "texture": "#1"}, "south": {"uv": [8.96, 4.96, 11.04, 7.04], "texture": "#1"}, "west": {"uv": [8.96, 4.96, 11.04, 7.04], "texture": "#1"}, "east": {"uv": [8.96, 4.96, 11.04, 7.04], "texture": "#1"}}}, {"__comment": "Voxels-111111", "from": [7.5, 6.5, 13.5], "to": [8, 7, 14], "faces": {"west": {"uv": [8.96, 4.96, 11.04, 7.04], "texture": "#1"}, "east": {"uv": [8.96, 4.96, 11.04, 7.04], "texture": "#1"}}}, {"__comment": "Voxels-111111", "from": [7.5, 6.5, 15], "to": [8, 8, 15.5], "faces": {"down": {"uv": [8.96, 4.96, 11.04, 7.04], "texture": "#1"}, "up": {"uv": [8.96, 4.96, 11.04, 7.04], "texture": "#1"}, "south": {"uv": [8.96, 4.96, 11.04, 7.04], "texture": "#1"}, "west": {"uv": [8.96, 4.96, 11.04, 7.04], "texture": "#1"}, "east": {"uv": [8.96, 4.96, 11.04, 7.04], "texture": "#1"}}}, {"__comment": "Voxels-111111", "from": [7.5, 7, 2.5], "to": [8, 7.5, 3], "faces": {"west": {"uv": [8.96, 4.96, 11.04, 7.04], "texture": "#1"}, "east": {"uv": [8.96, 4.96, 11.04, 7.04], "texture": "#1"}}}, {"__comment": "Voxels-111111", "from": [7.5, 7, 3.5], "to": [8, 9, 4.5], "faces": {"up": {"uv": [8.96, 4.96, 11.04, 7.04], "texture": "#1"}, "north": {"uv": [8.96, 4.96, 11.04, 7.04], "texture": "#1"}, "south": {"uv": [8.96, 4.96, 11.04, 7.04], "texture": "#1"}, "west": {"uv": [8.96, 4.96, 11.04, 7.04], "texture": "#1"}, "east": {"uv": [8.96, 4.96, 11.04, 7.04], "texture": "#1"}}}, {"__comment": "Voxels-111111", "from": [7.5, 7, 4.5], "to": [8, 8, 5], "faces": {"up": {"uv": [8.96, 4.96, 11.04, 7.04], "texture": "#1"}, "south": {"uv": [8.96, 4.96, 11.04, 7.04], "texture": "#1"}, "west": {"uv": [8.96, 4.96, 11.04, 7.04], "texture": "#1"}, "east": {"uv": [8.96, 4.96, 11.04, 7.04], "texture": "#1"}}}, {"__comment": "Voxels-111111", "from": [7.5, 7, 13], "to": [8, 7.5, 13.5], "faces": {"west": {"uv": [8.96, 4.96, 11.04, 7.04], "texture": "#1"}, "east": {"uv": [8.96, 4.96, 11.04, 7.04], "texture": "#1"}}}, {"__comment": "Voxels-111111", "from": [7.5, 7.5, 2], "to": [8, 9.5, 2.5], "faces": {"up": {"uv": [8.96, 4.96, 11.04, 7.04], "texture": "#1"}, "north": {"uv": [8.96, 4.96, 11.04, 7.04], "texture": "#1"}, "south": {"uv": [8.96, 4.96, 11.04, 7.04], "texture": "#1"}, "west": {"uv": [8.96, 4.96, 11.04, 7.04], "texture": "#1"}, "east": {"uv": [8.96, 4.96, 11.04, 7.04], "texture": "#1"}}}, {"__comment": "Voxels-111111", "from": [7.5, 7.5, 3], "to": [8, 9.5, 3.5], "faces": {"up": {"uv": [8.96, 4.96, 11.04, 7.04], "texture": "#1"}, "north": {"uv": [8.96, 4.96, 11.04, 7.04], "texture": "#1"}, "south": {"uv": [8.96, 4.96, 11.04, 7.04], "texture": "#1"}, "west": {"uv": [8.96, 4.96, 11.04, 7.04], "texture": "#1"}, "east": {"uv": [8.96, 4.96, 11.04, 7.04], "texture": "#1"}}}, {"__comment": "Voxels-4196CC", "from": [7.5, 7.5, 7], "to": [8.5, 8, 9], "faces": {"down": {"uv": [4.96, 0.96, 7.04, 3.04], "texture": "#1"}, "up": {"uv": [4.96, 0.96, 7.04, 3.04], "texture": "#1"}, "north": {"uv": [4.96, 0.96, 7.04, 3.04], "texture": "#1"}, "south": {"uv": [4.96, 0.96, 7.04, 3.04], "texture": "#1"}, "west": {"uv": [4.96, 0.96, 7.04, 3.04], "texture": "#1"}, "east": {"uv": [4.96, 0.96, 7.04, 3.04], "texture": "#1"}}}, {"__comment": "Voxels-111111", "from": [7.5, 7.5, 12.5], "to": [8, 9.5, 13], "faces": {"up": {"uv": [8.96, 4.96, 11.04, 7.04], "texture": "#1"}, "north": {"uv": [8.96, 4.96, 11.04, 7.04], "texture": "#1"}, "south": {"uv": [8.96, 4.96, 11.04, 7.04], "texture": "#1"}, "west": {"uv": [8.96, 4.96, 11.04, 7.04], "texture": "#1"}, "east": {"uv": [8.96, 4.96, 11.04, 7.04], "texture": "#1"}}}, {"__comment": "Voxels-111111", "from": [7.5, 7.5, 13.5], "to": [8, 9.5, 14], "faces": {"up": {"uv": [8.96, 4.96, 11.04, 7.04], "texture": "#1"}, "north": {"uv": [8.96, 4.96, 11.04, 7.04], "texture": "#1"}, "south": {"uv": [8.96, 4.96, 11.04, 7.04], "texture": "#1"}, "west": {"uv": [8.96, 4.96, 11.04, 7.04], "texture": "#1"}, "east": {"uv": [8.96, 4.96, 11.04, 7.04], "texture": "#1"}}}, {"__comment": "Voxels-111111", "from": [7.5, 8, 2.5], "to": [8, 9.5, 3], "faces": {"up": {"uv": [8.96, 4.96, 11.04, 7.04], "texture": "#1"}, "west": {"uv": [8.96, 4.96, 11.04, 7.04], "texture": "#1"}, "east": {"uv": [8.96, 4.96, 11.04, 7.04], "texture": "#1"}}}, {"__comment": "Voxels-111111", "from": [7.5, 8, 11.5], "to": [8, 9, 12.5], "faces": {"up": {"uv": [8.96, 4.96, 11.04, 7.04], "texture": "#1"}, "north": {"uv": [8.96, 4.96, 11.04, 7.04], "texture": "#1"}, "west": {"uv": [8.96, 4.96, 11.04, 7.04], "texture": "#1"}, "east": {"uv": [8.96, 4.96, 11.04, 7.04], "texture": "#1"}}}, {"__comment": "Voxels-111111", "from": [7.5, 8, 13], "to": [8, 9.5, 13.5], "faces": {"up": {"uv": [8.96, 4.96, 11.04, 7.04], "texture": "#1"}, "west": {"uv": [8.96, 4.96, 11.04, 7.04], "texture": "#1"}, "east": {"uv": [8.96, 4.96, 11.04, 7.04], "texture": "#1"}}}, {"__comment": "Voxels-4196CC", "from": [8, 7.5, 6.5], "to": [9.5, 8, 7], "faces": {"down": {"uv": [4.96, 0.96, 7.04, 3.04], "texture": "#1"}, "up": {"uv": [4.96, 0.96, 7.04, 3.04], "texture": "#1"}, "north": {"uv": [4.96, 0.96, 7.04, 3.04], "texture": "#1"}, "south": {"uv": [4.96, 0.96, 7.04, 3.04], "texture": "#1"}, "west": {"uv": [4.96, 0.96, 7.04, 3.04], "texture": "#1"}, "east": {"uv": [4.96, 0.96, 7.04, 3.04], "texture": "#1"}}}, {"__comment": "Voxels-4196CC", "from": [8, 7.5, 9], "to": [9.5, 8, 9.5], "faces": {"down": {"uv": [4.96, 0.96, 7.04, 3.04], "texture": "#1"}, "up": {"uv": [4.96, 0.96, 7.04, 3.04], "texture": "#1"}, "north": {"uv": [4.96, 0.96, 7.04, 3.04], "texture": "#1"}, "south": {"uv": [4.96, 0.96, 7.04, 3.04], "texture": "#1"}, "west": {"uv": [4.96, 0.96, 7.04, 3.04], "texture": "#1"}, "east": {"uv": [4.96, 0.96, 7.04, 3.04], "texture": "#1"}}}, {"__comment": "Voxels-4196CC", "from": [8, 8, 7.5], "to": [9.5, 8.5, 8.5], "faces": {"down": {"uv": [4.96, 0.96, 7.04, 3.04], "texture": "#1"}, "up": {"uv": [4.96, 0.96, 7.04, 3.04], "texture": "#1"}, "north": {"uv": [4.96, 0.96, 7.04, 3.04], "texture": "#1"}, "south": {"uv": [4.96, 0.96, 7.04, 3.04], "texture": "#1"}, "west": {"uv": [4.96, 0.96, 7.04, 3.04], "texture": "#1"}, "east": {"uv": [4.96, 0.96, 7.04, 3.04], "texture": "#1"}}}, {"__comment": "Voxels-0F0F0F", "from": [8.5, 6.5, 7], "to": [9, 7, 9], "faces": {"down": {"uv": [8.96, 0.96, 11.04, 3.04], "texture": "#1"}, "up": {"uv": [8.96, 0.96, 11.04, 3.04], "texture": "#1"}, "north": {"uv": [8.96, 0.96, 11.04, 3.04], "texture": "#1"}, "south": {"uv": [8.96, 0.96, 11.04, 3.04], "texture": "#1"}, "west": {"uv": [8.96, 0.96, 11.04, 3.04], "texture": "#1"}, "east": {"uv": [8.96, 0.96, 11.04, 3.04], "texture": "#1"}}}, {"__comment": "Voxels-4196CC", "from": [8.5, 8, 7], "to": [9.5, 8.5, 7.5], "faces": {"down": {"uv": [4.96, 0.96, 7.04, 3.04], "texture": "#1"}, "up": {"uv": [4.96, 0.96, 7.04, 3.04], "texture": "#1"}, "north": {"uv": [4.96, 0.96, 7.04, 3.04], "texture": "#1"}, "west": {"uv": [4.96, 0.96, 7.04, 3.04], "texture": "#1"}, "east": {"uv": [4.96, 0.96, 7.04, 3.04], "texture": "#1"}}}, {"__comment": "Voxels-4196CC", "from": [8.5, 8, 8.5], "to": [9.5, 8.5, 9], "faces": {"down": {"uv": [4.96, 0.96, 7.04, 3.04], "texture": "#1"}, "up": {"uv": [4.96, 0.96, 7.04, 3.04], "texture": "#1"}, "south": {"uv": [4.96, 0.96, 7.04, 3.04], "texture": "#1"}, "west": {"uv": [4.96, 0.96, 7.04, 3.04], "texture": "#1"}, "east": {"uv": [4.96, 0.96, 7.04, 3.04], "texture": "#1"}}}, {"__comment": "Voxels-0F0F0F", "from": [9, 6.5, 7.5], "to": [9.5, 7, 8.5], "faces": {"down": {"uv": [8.96, 0.96, 11.04, 3.04], "texture": "#1"}, "up": {"uv": [8.96, 0.96, 11.04, 3.04], "texture": "#1"}, "north": {"uv": [8.96, 0.96, 11.04, 3.04], "texture": "#1"}, "south": {"uv": [8.96, 0.96, 11.04, 3.04], "texture": "#1"}, "east": {"uv": [8.96, 0.96, 11.04, 3.04], "texture": "#1"}}}, {"__comment": "Voxels-4196CC", "from": [9, 7, 7], "to": [9.5, 7.5, 7.5], "faces": {"down": {"uv": [4.96, 0.96, 7.04, 3.04], "texture": "#1"}, "up": {"uv": [4.96, 0.96, 7.04, 3.04], "texture": "#1"}, "north": {"uv": [4.96, 0.96, 7.04, 3.04], "texture": "#1"}, "south": {"uv": [4.96, 0.96, 7.04, 3.04], "texture": "#1"}, "west": {"uv": [4.96, 0.96, 7.04, 3.04], "texture": "#1"}, "east": {"uv": [4.96, 0.96, 7.04, 3.04], "texture": "#1"}}}, {"__comment": "Voxels-4196CC", "from": [9, 7, 8.5], "to": [9.5, 7.5, 9], "faces": {"down": {"uv": [4.96, 0.96, 7.04, 3.04], "texture": "#1"}, "up": {"uv": [4.96, 0.96, 7.04, 3.04], "texture": "#1"}, "north": {"uv": [4.96, 0.96, 7.04, 3.04], "texture": "#1"}, "south": {"uv": [4.96, 0.96, 7.04, 3.04], "texture": "#1"}, "west": {"uv": [4.96, 0.96, 7.04, 3.04], "texture": "#1"}, "east": {"uv": [4.96, 0.96, 7.04, 3.04], "texture": "#1"}}}, {"__comment": "Voxels-4196CC", "from": [9.5, 7, 7.5], "to": [10, 8, 8.5], "faces": {"down": {"uv": [4.96, 0.96, 7.04, 3.04], "texture": "#1"}, "up": {"uv": [4.96, 0.96, 7.04, 3.04], "texture": "#1"}, "north": {"uv": [4.96, 0.96, 7.04, 3.04], "texture": "#1"}, "south": {"uv": [4.96, 0.96, 7.04, 3.04], "texture": "#1"}, "west": {"uv": [4.96, 0.96, 7.04, 3.04], "texture": "#1"}, "east": {"uv": [4.96, 0.96, 7.04, 3.04], "texture": "#1"}}}, {"__comment": "Voxels-4196CC", "from": [9.5, 7.5, 7], "to": [10, 8, 7.5], "faces": {"down": {"uv": [4.96, 0.96, 7.04, 3.04], "texture": "#1"}, "up": {"uv": [4.96, 0.96, 7.04, 3.04], "texture": "#1"}, "north": {"uv": [4.96, 0.96, 7.04, 3.04], "texture": "#1"}, "west": {"uv": [4.96, 0.96, 7.04, 3.04], "texture": "#1"}, "east": {"uv": [4.96, 0.96, 7.04, 3.04], "texture": "#1"}}}, {"__comment": "Voxels-4196CC", "from": [9.5, 7.5, 8.5], "to": [10, 8, 9], "faces": {"down": {"uv": [4.96, 0.96, 7.04, 3.04], "texture": "#1"}, "up": {"uv": [4.96, 0.96, 7.04, 3.04], "texture": "#1"}, "south": {"uv": [4.96, 0.96, 7.04, 3.04], "texture": "#1"}, "west": {"uv": [4.96, 0.96, 7.04, 3.04], "texture": "#1"}, "east": {"uv": [4.96, 0.96, 7.04, 3.04], "texture": "#1"}}}], "display": {"thirdperson_righthand": {"translation": [0, 3.4781, -2.086], "scale": [0.8, 0.8, 0.8]}, "thirdperson_lefthand": {"translation": [0, 3.4781, -2.086], "scale": [0.8, 0.8, 0.8]}, "firstperson_righthand": {"translation": [0, 4.8695, 0]}, "firstperson_lefthand": {"translation": [0, 4.8695, 0]}, "gui": {"rotation": [9, -106, 0], "translation": [-0.2, 2.7825, 0]}, "head": {"rotation": [0, 90, 0], "translation": [0, 9.7391, -1.39], "scale": [1.65, 1.65, 1.65]}, "ground": {"translation": [0, 4.8695, 0]}, "fixed": {"rotation": [0, 90, 0], "translation": [0, 4.1739, 0], "scale": [1.3, 1.3, 1.3]}}}