{
    "parent": "block/carved_pumpkin",
    "textures": {
        "layer0": "block/carved_pumpkin"
    },
    "overrides": [
        {
            "predicate": {
                "custom_model_data": 1
            },
            "model": "custom/gear/hats/aviators"
        },
        {
            "predicate": {
                "custom_model_data": 2
            },
            "model": "custom/gear/hats/bender"
        },
        {
            "predicate": {
                "custom_model_data": 3
            },
            "model": "custom/gear/hats/bobross"
        },
        {
            "predicate": {
                "custom_model_data": 4
            },
            "model": "custom/gear/hats/bowler"
        },
        {
            "predicate": {
                "custom_model_data": 5
            },
            "model": "custom/gear/hats/captainhat"
        },
        {
            "predicate": {
                "custom_model_data": 6
            },
            "model": "custom/gear/hats/chefhat"
        },
        {
            "predicate": {
                "custom_model_data": 7
            },
            "model": "custom/gear/hats/conehat"
        },
        {
            "predicate": {
                "custom_model_data": 8
            },
            "model": "custom/gear/hats/davyjones"
        },
        {
            "predicate": {
                "custom_model_data": 9
            },
            "model": "custom/gear/hats/divehelmet"
        },
        {
            "predicate": {
                "custom_model_data": 10
            },
            "model": "custom/gear/hats/donaldcap"
        },
        {
            "predicate": {
                "custom_model_data": 11
            },
            "model": "custom/gear/hats/drfhat"
        },
        {
            "predicate": {
                "custom_model_data": 12
            },
            "model": "custom/gear/hats/goofycap"
        },
        {
            "predicate": {
                "custom_model_data": 13
            },
            "model": "custom/gear/hats/hunny"
        },
        {
            "predicate": {
                "custom_model_data": 14
            },
            "model": "custom/gear/hats/incredimask"
        },
        {
            "predicate": {
                "custom_model_data": 15
            },
            "model": "custom/gear/hats/jacksparrow"
        },
        {
            "predicate": {
                "custom_model_data": 16
            },
            "model": "custom/gear/hats/jafar"
        },
        {
            "predicate": {
                "custom_model_data": 17
            },
            "model": "custom/gear/hats/luigihat"
        },
        {
            "predicate": {
                "custom_model_data": 18
            },
            "model": "custom/gear/hats/mannycap"
        },
        {
            "predicate": {
                "custom_model_data": 19
            },
            "model": "custom/gear/hats/matercap"
        },
        {
            "predicate": {
                "custom_model_data": 20
            },
            "model": "custom/gear/hats/mistletoehat"
        },
        {
            "predicate": {
                "custom_model_data": 21
            },
            "model": "custom/gear/hats/oogiehat"
        },
        {
            "predicate": {
                "custom_model_data": 22
            },
            "model": "custom/gear/hats/patriotic"
        },
        {
            "predicate": {
                "custom_model_data": 23
            },
            "model": "custom/gear/hats/perrycap"
        },
        {
            "predicate": {
                "custom_model_data": 24
            },
            "model": "custom/gear/hats/plutocap"
        },
        {
            "predicate": {
                "custom_model_data": 25
            },
            "model": "custom/gear/hats/santahat"
        },
        {
            "predicate": {
                "custom_model_data": 26
            },
            "model": "custom/gear/hats/snowmancap"
        },
        {
            "predicate": {
                "custom_model_data": 27
            },
            "model": "custom/gear/hats/soldierhat"
        },
        {
            "predicate": {
                "custom_model_data": 28
            },
            "model": "custom/gear/hats/tot"
        },
        {
            "predicate": {
                "custom_model_data": 29
            },
            "model": "custom/gear/hats/turkeyhat"
        },
        {
            "predicate": {
                "custom_model_data": 30
            },
            "model": "custom/gear/hats/witchhat"
        },
        {
            "predicate": {
                "custom_model_data": 31
            },
            "model": "custom/gear/hats/squid_hat"
        },
        {
            "predicate": {
                "custom_model_data": 32
            },
            "model": "custom/gear/headbands/alienhb"
        },
        {
            "predicate": {
                "custom_model_data": 33
            },
            "model": "custom/gear/headbands/arielhb"
        },
        {
            "predicate": {
                "custom_model_data": 34
            },
            "model": "custom/gear/headbands/bingbonghb"
        },
        {
            "predicate": {
                "custom_model_data": 35
            },
            "model": "custom/gear/headbands/bwminniehb"
        },
        {
            "predicate": {
                "custom_model_data": 36
            },
            "model": "custom/gear/headbands/candycornhb"
        },
        {
            "predicate": {
                "custom_model_data": 37
            },
            "model": "custom/gear/headbands/caphb"
        },
        {
            "predicate": {
                "custom_model_data": 38
            },
            "model": "custom/gear/headbands/chernabog"
        },
        {
            "predicate": {
                "custom_model_data": 39
            },
            "model": "custom/gear/headbands/classicminniehb"
        },
        {
            "predicate": {
                "custom_model_data": 40
            },
            "model": "custom/gear/headbands/devilhb"
        },
        {
            "predicate": {
                "custom_model_data": 41
            },
            "model": "custom/gear/headbands/dolehb"
        },
        {
            "predicate": {
                "custom_model_data": 42
            },
            "model": "custom/gear/headbands/donaldbutthb"
        },
        {
            "predicate": {
                "custom_model_data": 43
            },
            "model": "custom/gear/headbands/donaldhb2"
        },
        {
            "predicate": {
                "custom_model_data": 44
            },
            "model": "custom/gear/headbands/donuthb"
        },
        {
            "predicate": {
                "custom_model_data": 45
            },
            "model": "custom/gear/headbands/dumbohb"
        },
        {
            "predicate": {
                "custom_model_data": 46
            },
            "model": "custom/gear/headbands/gingerbreadhb"
        },
        {
            "predicate": {
                "custom_model_data": 47
            },
            "model": "custom/gear/headbands/millenialpinkhb"
        },
        {
            "predicate": {
                "custom_model_data": 48
            },
            "model": "custom/gear/headbands/ortensiahb"
        },
        {
            "predicate": {
                "custom_model_data": 49
            },
            "model": "custom/gear/headbands/ortensiahhb1"
        },
        {
            "predicate": {
                "custom_model_data": 50
            },
            "model": "custom/gear/headbands/oswaldhb"
        },
        {
            "predicate": {
                "custom_model_data": 51
            },
            "model": "custom/gear/headbands/pepperminthb"
        },
        {
            "predicate": {
                "custom_model_data": 52
            },
            "model": "custom/gear/headbands/tothb2"
        },
        {
            "predicate": {
                "custom_model_data": 53
            },
            "model": "custom/gear/hats/clown"
        },
        {
            "predicate": {
                "custom_model_data": 54
            },
            "model": "custom/gear/hats/gmrcast"
        },
        {
            "predicate": {
                "custom_model_data": 55
            },
            "model": "custom/gear/hats/halloween"
        },
        {
            "predicate": {
                "custom_model_data": 56
            },
            "model": "custom/gear/hats/happymeal"
        },
        {
            "predicate": {
                "custom_model_data": 57
            },
            "model": "custom/gear/hats/harryhat"
        },
        {
            "predicate": {
                "custom_model_data": 58
            },
            "model": "custom/gear/hats/homer_head"
        },
        {
            "predicate": {
                "custom_model_data": 59
            },
            "model": "custom/gear/hats/loki"
        },
        {
            "predicate": {
                "custom_model_data": 60
            },
            "model": "custom/gear/hats/longhornhat"
        },
        {
            "predicate": {
                "custom_model_data": 61
            },
            "model": "custom/gear/hats/luxo"
        },
        {
            "predicate": {
                "custom_model_data": 62
            },
            "model": "custom/gear/hats/magicianhat"
        },
        {
            "predicate": {
                "custom_model_data": 63
            },
            "model": "custom/gear/hats/maleficent"
        },
        {
            "predicate": {
                "custom_model_data": 64
            },
            "model": "custom/gear/headbands/patriotichb"
        },
        {
            "predicate": {
                "custom_model_data": 65
            },
            "model": "custom/gear/hats/pilot"
        },
        {
            "predicate": {
                "custom_model_data": 66
            },
            "model": "custom/gear/hats/racoonhat"
        },
        {
            "predicate": {
                "custom_model_data": 67
            },
            "model": "custom/gear/hats/tntbarrel"
        },
        {
            "predicate": {
                "custom_model_data": 68
            },
            "model": "custom/gear/hats/sidbaby"
        },
        {
            "predicate": {
                "custom_model_data": 69
            },
            "model": "custom/gear/hats/angelmickeyearhat"
        },
        {
            "predicate": {
                "custom_model_data": 70
            },
            "model": "custom/gear/hats/baymaxearhat"
        },
        {
            "predicate": {
                "custom_model_data": 71
            },
            "model": "custom/gear/hats/bellhopearhat"
        },
        {
            "predicate": {
                "custom_model_data": 72
            },
            "model": "custom/gear/hats/bluemickeyearhat"
        },
        {
            "predicate": {
                "custom_model_data": 73
            },
            "model": "custom/gear/hats/buzzearhat"
        },
        {
            "predicate": {
                "custom_model_data": 74
            },
            "model": "custom/gear/hats/chipearhat"
        },
        {
            "predicate": {
                "custom_model_data": 75
            },
            "model": "custom/gear/hats/daleearhat"
        },
        {
            "predicate": {
                "custom_model_data": 76
            },
            "model": "custom/gear/hats/dolewhipearhat"
        },
        {
            "predicate": {
                "custom_model_data": 77
            },
            "model": "custom/gear/hats/eveearhat"
        },
        {
            "predicate": {
                "custom_model_data": 78
            },
            "model": "custom/gear/hats/icecreamearhat"
        },
        {
            "predicate": {
                "custom_model_data": 79
            },
            "model": "custom/gear/hats/jackskellingtonearhat"
        },
        {
            "predicate": {
                "custom_model_data": 80
            },
            "model": "custom/gear/hats/kermitearhat"
        },
        {
            "predicate": {
                "custom_model_data": 81
            },
            "model": "custom/gear/hats/limemickeyearhat"
        },
        {
            "predicate": {
                "custom_model_data": 82
            },
            "model": "custom/gear/hats/mickeyfaceearhat"
        },
        {
            "predicate": {
                "custom_model_data": 83
            },
            "model": "custom/gear/hats/mickeymouseclubearhat"
        },
        {
            "predicate": {
                "custom_model_data": 84
            },
            "model": "custom/gear/hats/pinkmickeyearhat"
        },
        {
            "predicate": {
                "custom_model_data": 85
            },
            "model": "custom/gear/hats/poohearhat"
        },
        {
            "predicate": {
                "custom_model_data": 86
            },
            "model": "custom/gear/hats/purplemickeyearhat"
        },
        {
            "predicate": {
                "custom_model_data": 87
            },
            "model": "custom/gear/hats/r2d2mickeyearhat"
        },
        {
            "predicate": {
                "custom_model_data": 88
            },
            "model": "custom/gear/hats/redmickeyearhat"
        },
        {
            "predicate": {
                "custom_model_data": 89
            },
            "model": "custom/gear/hats/remyearhat"
        },
        {
            "predicate": {
                "custom_model_data": 90
            },
            "model": "custom/gear/hats/retroearhat"
        },
        {
            "predicate": {
                "custom_model_data": 91
            },
            "model": "custom/gear/hats/steamboatwillieearhat"
        },
        {
            "predicate": {
                "custom_model_data": 92
            },
            "model": "custom/gear/hats/steamboatwilliefaceearhat"
        },
        {
            "predicate": {
                "custom_model_data": 93
            },
            "model": "custom/gear/hats/stitchmickeyearhat"
        },
        {
            "predicate": {
                "custom_model_data": 94
            },
            "model": "custom/gear/hats/tealmickeyearhat"
        },
        {
            "predicate": {
                "custom_model_data": 95
            },
            "model": "custom/gear/hats/yodaearhat"
        },
        {
            "predicate": {
                "custom_model_data": 96
            },
            "model": "custom/gear/hats/zombiemickeyearhat"
        }
    ]
}